{
  "appShortName": "Kailasa",
  "appName": "Kailasa App – Supreme Intelligence for AI in Finance, Health & Happiness",
  "companyName": "IGURU INNOVATIONS LLC",
  "siteTitle": "Kailasa App – Supreme Intelligence for AI in Finance, Health & Happiness (Staging)",
  "appStoreUrl": "https://apps.apple.com/us/app/kailasa-supreme-intelligence/id6743522351",
  "playStoreUrl": "https://play.google.com/store/apps/details?id=app.kailasa",
  "webAppUrl": "https://web-stg.kailasa.app",
  "contactApiUrl":"https://api-stg.kailasa.app/v1/website/contact-us",
  "subscriptionApiUrl":"https://api-stg.kailasa.app/v1/website/subscribe-newsletter",
  "videoId": "dY-1dGS5XII",
  "allaboutdnt": "http://www.allaboutdnt.com",
  "adr": "http://www.adr.org",
  "consumerArbitration":"http://www.adr.org/consumer_arbitration",
  "linkedInSatya": "https://www.linkedin.com/in/satya-dillikar/",
  "linkedInSavir": "https://www.linkedin.com/in/savir-dillikar/",
  "kailasaAppUrl": "https://www.Kailasa.app",
  "kailasaAppDomain": "www.Kailasa.app",
  "kailasaApp": "Kailasa.app",
  "youtubeKailasa": "https://www.youtube.com/@KailasaApp",
  "linkedInKailasa": "https://www.linkedin.com/company/kailasa-app/",
  "instagramKailasa": "https://www.instagram.com/kailasa.app/",
  "facebookKailasa": "https://www.facebook.com/profile.php?id=61572950619780",
  "infoEmail": "info@kailasa.app",
  "supportEmail":"support@kailasa.app",
  "officeAddress":"San Francisco, California, United States"
}
